transformational_measures_tf/__init__.py
transformational_measures_tf/analyzer.py
transformational_measures_tf/cifar10transformations.py
transformational_measures_tf/dataset.py
transformational_measures_tf/featuresvariance.py
transformational_measures_tf/graphs.py
transformational_measures_tf/iterator.py
transformational_measures_tf/metric.py
transformational_measures_tf/mnisttransformations.py
transformational_measures_tf/model.py
transformational_measures_tf/normalizedfeaturesvariance.py
transformational_measures_tf/normalizedsameequivariance.py
transformational_measures_tf/normalizedvariance.py
transformational_measures_tf/sameequivariance.py
transformational_measures_tf/transformations.py
transformational_measures_tf/transformationsdataset.py
transformational_measures_tf/variance.py
transformational_measures_tf-0.72a0.dist-info/LICENSE
transformational_measures_tf-0.72a0.dist-info/METADATA
transformational_measures_tf-0.72a0.dist-info/WHEEL
transformational_measures_tf-0.72a0.dist-info/top_level.txt
transformational_measures_tf-0.72a0.dist-info/zip-safe
transformational_measures_tf-0.72a0.dist-info/RECORD
