Metadata-Version: 2.1
Name: transformational-measures-tf
Version: 0.72a0
Summary: Invariance, Same-Equivariance and other measures for Neural Networks. Support for TensorFlow.
Home-page: https://github.com/midusi/transformational_measures_tf/
Author: Federico Ravettino, Facundo Manuel Quiroga
Author-email: facundoq@gmail.com
License: UNKNOWN
Project-URL: Bug Tracker, https://github.com/midusi/transformational_measures_tf//issues
Project-URL: Documentation, https://github.com/midusi/transformational_measures_tf/
Project-URL: Source Code, https://github.com/midusi/transformational_measures_tf/
Keywords: transformational measures equivariance same-equivariance invariance variance neural networks python pytorch numpy tensorflow
Platform: UNKNOWN
Classifier: License :: OSI Approved :: Python Software Foundation License
Classifier: License :: OSI Approved :: GNU Affero General Public License v3 or later (AGPLv3+)
Classifier: Development Status :: 4 - Beta
Classifier: Topic :: Scientific/Engineering :: Artificial Intelligence
Classifier: Topic :: Scientific/Engineering :: Visualization
Requires-Python: >=3.6
Requires-Dist: numpy
Requires-Dist: scipy
Requires-Dist: keras
Requires-Dist: matplotlib
Requires-Dist: tqdm
